npf/__init__.py
npf/misc.py
npf/jax/__init__.py
npf/jax/functional.py
npf/jax/typing.py
npf/jax/utils.py
npf/jax/data/__init__.py
npf/jax/data/base.py
npf/jax/data/build.py
npf/jax/data/gp.py
npf/jax/data/image.py
npf/jax/data/save.py
npf/jax/data/sim2real.py
npf/jax/models/__init__.py
npf/jax/models/anp.py
npf/jax/models/base.py
npf/jax/models/bnp.py
npf/jax/models/canp.py
npf/jax/models/cnp.py
npf/jax/models/convcnp.py
npf/jax/models/convnp.py
npf/jax/models/neubnp.py
npf/jax/models/np.py
npf/jax/modules/__init__.py
npf/jax/modules/attention.py
npf/jax/modules/cnn.py
npf/jax/modules/net.py
npf/jax/modules/setconv.py
np_family-0.2.0.dist-info/LICENSE
np_family-0.2.0.dist-info/METADATA
np_family-0.2.0.dist-info/WHEEL
np_family-0.2.0.dist-info/top_level.txt
np_family-0.2.0.dist-info/zip-safe
np_family-0.2.0.dist-info/RECORD
