Metadata-Version: 2.1
Name: np-family
Version: 0.2.0
Summary: Neural Processes implementations in JAX and PyTorch
Home-page: https://github.com/yuneg11/Neural-Process-Family
Author: EungGu Yun
Author-email: yuneg11@gmail.com
License: MIT license
Project-URL: Documentation, https://yuneg11.github.io/Neural-Process-Family
Project-URL: Source, https://github.com/yuneg11/Neural-Process-Family
Project-URL: Tracker, https://github.com/yuneg11/Neural-Process-Family/issues
Keywords: npf,NPF,neural process
Classifier: Operating System :: OS Independent
Classifier: License :: OSI Approved :: MIT License
Classifier: Programming Language :: Python :: 3
Classifier: Programming Language :: Python :: 3.7
Classifier: Programming Language :: Python :: 3.8
Classifier: Programming Language :: Python :: 3.9
Classifier: Programming Language :: Python :: 3.10
Classifier: Topic :: Scientific/Engineering :: Artificial Intelligence
Classifier: Topic :: Software Development :: Libraries :: Python Modules
Requires-Python: >=3.7
License-File: LICENSE
